passninja/__init__.py
passninja/passninja.py
passninja-1.4.0.dist-info/METADATA
passninja-1.4.0.dist-info/WHEEL
passninja-1.4.0.dist-info/licenses/LICENSE
passninja-1.4.0.dist-info/RECORD
