Metadata-Version: 2.1
Name: passninja
Version: 1.4.0
Summary: PassNinja API library for Python
Project-URL: Homepage, https://github.com/flomio/passninja-python
Project-URL: Bug Tracker, https://github.com/flomio/passninja-python/issues
Author-email: PassNinja <info@passninja.com>
License-File: LICENSE
Classifier: License :: OSI Approved :: MIT License
Classifier: Operating System :: OS Independent
Classifier: Programming Language :: Python :: 3
Requires-Python: >=3.7
